pngdata/__init__.py
pngdata/__main__.py
pngdata/core.py
pngdata-1.0.0.dist-info/LICENSE
pngdata-1.0.0.dist-info/METADATA
pngdata-1.0.0.dist-info/WHEEL
pngdata-1.0.0.dist-info/top_level.txt
pngdata-1.0.0.dist-info/RECORD
