Metadata-Version: 2.1
Name: pngdata
Version: 1.0.0
Summary: Write data to PNG file format
Home-page: https://github.com/kugo12/pngdata
Author: kvgx12
License: MIT
Platform: UNKNOWN
Classifier: Programming Language :: Python :: 3
Classifier: License :: OSI Approved :: MIT License
Classifier: Operating System :: OS Independent
Requires-Python: >=3.6
Requires-Dist: Pillow
